LICENSE
MANIFEST.in
README.md
requirements-dev.txt
requirements-tests.txt
requirements.txt
setup.cfg
setup.py
cli/__init__.py
cli/entrypoint.py
pattern_recognition_cli.egg-info/PKG-INFO
pattern_recognition_cli.egg-info/SOURCES.txt
pattern_recognition_cli.egg-info/dependency_links.txt
pattern_recognition_cli.egg-info/entry_points.txt
pattern_recognition_cli.egg-info/requires.txt
pattern_recognition_cli.egg-info/top_level.txt
tests/__init__.py
tests/test_entrypoint.py