Metadata-Version: 2.1
Name: pattern-recognition-cli
Version: 0.1.1
Summary: The command-line interface (CLI) that provides a set of commands for pattern recognition by interacting with the server
Home-page: https://github.com/Alladin9393/Pattern-recognition
Author: Alladin9393
Author-email: ember.toon@protonmail.com
License: MIT
Platform: UNKNOWN
Classifier: Operating System :: OS Independent
Classifier: Intended Audience :: Developers
Classifier: License :: OSI Approved :: MIT License
Classifier: Programming Language :: Python :: 3.4
Classifier: Programming Language :: Python :: 3.5
Classifier: Programming Language :: Python :: 3.6
Classifier: Programming Language :: Python :: 3.7
